<?xml version="1.0" encoding="utf-8" ?>
<dwsync>
<file name="bg.png" server="ftp.solitaireinfosys.com/public_html/" local="129797184342874168" remote="129800792400000000" />
<file name="left_div.png" server="ftp.solitaireinfosys.com/public_html/" local="129797184348654499" remote="129800792400000000" />
<file name="center_div3.png" server="ftp.solitaireinfosys.com/public_html/" local="129797184344344252" remote="129800792400000000" />
<file name="icon_1.png" server="ftp.solitaireinfosys.com/public_html/" local="129797184347994461" remote="129800792400000000" />
<file name="right_div.png" server="ftp.solitaireinfosys.com/public_html/" local="129797184351104639" remote="129800792400000000" />
<file name="icon_2.png" server="ftp.solitaireinfosys.com/public_html/" local="129797184348054465" remote="129800792400000000" />
<file name="icon_3.png" server="ftp.solitaireinfosys.com/public_html/" local="129797184348114468" remote="129800792400000000" />
<file name="icon_4.png" server="ftp.solitaireinfosys.com/public_html/" local="129797184348174471" remote="129800792400000000" />
<file name="icon_5.png" server="ftp.solitaireinfosys.com/public_html/" local="129797184348234475" remote="129800792400000000" />
<file name="icon_6.png" server="ftp.solitaireinfosys.com/public_html/" local="129797184348304479" remote="129800792400000000" />
<file name="upper_div1.png" server="ftp.solitaireinfosys.com/public_html/" local="129797184352984746" remote="129800792400000000" />
<file name="bottom_div2.png" server="ftp.solitaireinfosys.com/public_html/" local="129797184343214188" remote="129800792400000000" />
<file name="center_div1.png" server="ftp.solitaireinfosys.com/public_html/" local="129797184344284249" remote="129800792400000000" />
<file name="login_box.png" server="ftp.solitaireinfosys.com/public_html/" local="129797184349104525" remote="129800792400000000" />
<file name="2.png" server="ftp.solitaireinfosys.com/public_html/" local="129797184341254076" remote="129800795400000000" />
<file name="button3.png" server="ftp.solitaireinfosys.com/public_html/" local="129797184343824223" remote="129800795400000000" />
<file name="choose.gif" server="ftp.solitaireinfosys.com/public_html/" local="129797184344474260" remote="129800795400000000" />
<file name="submit_button.png" server="ftp.solitaireinfosys.com/public_html/" local="129797184351654670" remote="129800795400000000" />
<file name="submit_button1.png" server="ftp.solitaireinfosys.com/public_html/" local="129797184351954688" remote="129800795400000000" />
<file name="submit_button2.png" server="ftp.solitaireinfosys.com/public_html/" local="129797184352024692" remote="129800795400000000" />
<file name="header.png" server="ftp.solitaireinfosys.com/public_html/" local="129797184347894455" remote="129800795400000000" />
<file name="add_catagory_button.png" server="ftp.solitaireinfosys.com/public_html/" local="129797184341424085" remote="129800795400000000" />
<file name="add.png" server="ftp.solitaireinfosys.com/public_html/" local="129797184341364082" remote="129800795400000000" />
<file name="export.png" server="ftp.solitaireinfosys.com/public_html/" local="129797184347374426" remote="129800795400000000" />
<file name="search_bar.png" server="ftp.solitaireinfosys.com/public_html/" local="129797184351314651" remote="129800795400000000" />
<file name="search_button.png" server="ftp.solitaireinfosys.com/public_html/" local="129797184351374654" remote="129800795400000000" />
<file name="button5.png" server="ftp.solitaireinfosys.com/public_html/" local="129797184343884226" remote="129800795400000000" />
<file name="add_subcatagory_button.png" server="ftp.solitaireinfosys.com/public_html/" local="129797184341714102" remote="129800795400000000" />
<file name="edit_.png" server="ftp.solitaireinfosys.com/public_html/" local="129797184346884398" remote="129800795400000000" />
<file name="popup_bg.png" server="ftp.solitaireinfosys.com/public_html/" local="129797184350494604" remote="129800795400000000" />
<file name="cross.png" server="ftp.solitaireinfosys.com/public_html/" local="129797184345194301" remote="129800795400000000" />
<file name="button.png" server="ftp.solitaireinfosys.com/public_html/" local="129797184343614211" remote="129800795400000000" />
<file name="delete_selected.png" server="ftp.solitaireinfosys.com/public_html/" local="129797184345764334" remote="129800795400000000" />
<file name="main_bg.png" server="ftp.solitaireinfosys.com/public_html/" local="129797184349854567" remote="129800795400000000" />
<file name="text_box.png" server="ftp.solitaireinfosys.com/public_html/" local="129797184352394713" remote="129800795400000000" />
<file name="move.png" server="ftp.solitaireinfosys.com/public_html/" local="129797184350164585" remote="129800795400000000" />
<file name="reset.png" server="ftp.solitaireinfosys.com/public_html/" local="129797184350804622" remote="129800795400000000" />
<file name="cal.gif" server="ftp.solitaireinfosys.com/public_html/" local="129797184344054236" remote="129800795400000000" />
</dwsync>